mkdoxy/DoxyTagParser.py
mkdoxy/__init__.py
mkdoxy/cache.py
mkdoxy/constants.py
mkdoxy/doxygen.py
mkdoxy/doxyrun.py
mkdoxy/filters.py
mkdoxy/finder.py
mkdoxy/generatorAuto.py
mkdoxy/generatorBase.py
mkdoxy/generatorSnippets.py
mkdoxy/markdown.py
mkdoxy/node.py
mkdoxy/plugin.py
mkdoxy/project.py
mkdoxy/property.py
mkdoxy/utils.py
mkdoxy/xml_parser.py
mkdoxy/templates/annotated.jinja2
mkdoxy/templates/classes.jinja2
mkdoxy/templates/code.jinja2
mkdoxy/templates/error.jinja2
mkdoxy/templates/example.jinja2
mkdoxy/templates/examples.jinja2
mkdoxy/templates/files.jinja2
mkdoxy/templates/hierarchy.jinja2
mkdoxy/templates/index.jinja2
mkdoxy/templates/memDef.jinja2
mkdoxy/templates/memTab.jinja2
mkdoxy/templates/member.jinja2
mkdoxy/templates/modules.jinja2
mkdoxy/templates/namespaces.jinja2
mkdoxy/templates/page.jinja2
mkdoxy/templates/programlisting.jinja2
mkdoxy/templates/relatedPages.jinja2
mkdoxy-1.2.8.dist-info/licenses/LICENSE
mkdoxy-1.2.8.dist-info/METADATA
mkdoxy-1.2.8.dist-info/WHEEL
mkdoxy-1.2.8.dist-info/entry_points.txt
mkdoxy-1.2.8.dist-info/top_level.txt
mkdoxy-1.2.8.dist-info/RECORD
