Metadata-Version: 2.4
Name: mkdoxy
Version: 1.2.8
Summary: MkDoxy → MkDocs + Doxygen = easy documentation generator with code snippets
Home-page: https://github.com/JakubAndrysek/MkDoxy
Author: Jakub Andrýsek
Author-email: email@kubaandrysek.cz
License: MIT
Project-URL: Source, https://github.com/JakubAndrysek/MkDoxy
Project-URL: Documentation, https://mkdoxy.kubaandrysek.cz/
Project-URL: Tracker, https://github.com/JakubAndrysek/MkDoxy/issues
Project-URL: Funding, https://github.com/sponsors/jakubandrysek
Keywords: mkdoxy,python,open-source,documentation,mkdocs,doxygen,multilanguage,code-snippets,code,snippets,documentation-generator
Classifier: Programming Language :: Python :: 3.9
Classifier: Programming Language :: Python :: 3.10
Classifier: Programming Language :: Python :: 3.11
Classifier: Programming Language :: Python :: 3.12
Classifier: Operating System :: OS Independent
Requires-Python: >=3.9
License-File: LICENSE
Requires-Dist: mkdocs
Provides-Extra: dev
Requires-Dist: mkdocs-material~=9.6.18; extra == "dev"
Requires-Dist: mkdocs-open-in-new-tab~=1.0.8; extra == "dev"
Requires-Dist: pathlib~=1.0.1; extra == "dev"
Requires-Dist: isort~=6.0.1; extra == "dev"
Requires-Dist: pytest~=8.4.1; extra == "dev"
Requires-Dist: pre-commit~=4.3.0; extra == "dev"
Requires-Dist: setuptools~=80.9.0; extra == "dev"
Requires-Dist: build~=1.3.0; extra == "dev"
Requires-Dist: twine~=6.1.0; extra == "dev"
Dynamic: author
Dynamic: author-email
Dynamic: classifier
Dynamic: description
Dynamic: description-content-type
Dynamic: home-page
Dynamic: keywords
Dynamic: license
Dynamic: license-file
Dynamic: project-url
Dynamic: provides-extra
Dynamic: requires-dist
Dynamic: requires-python
Dynamic: summary
